langchain_opendataloader_pdf/__init__.py
langchain_opendataloader_pdf/document_loaders.py
langchain_opendataloader_pdf/py.typed
langchain_opendataloader_pdf-0.0.2.dist-info/METADATA
langchain_opendataloader_pdf-0.0.2.dist-info/WHEEL
langchain_opendataloader_pdf-0.0.2.dist-info/licenses/LICENSE
langchain_opendataloader_pdf-0.0.2.dist-info/RECORD
