Metadata-Version: 2.4
Name: langchain-opendataloader-pdf
Version: 0.0.2
Summary: A LangChain integration for OpenDataLoader PDF
License-Expression: MIT
License-File: LICENSE
Keywords: langchain,dataloader,pdf,document loader,ai,document-parsing,document
Author: opendataloader-project
Author-email: open.dataloader@hancom.com
Requires-Python: >=3.9,<4.0
Classifier: Development Status :: 4 - Beta
Classifier: Intended Audience :: Developers
Classifier: Intended Audience :: Science/Research
Classifier: Operating System :: OS Independent
Classifier: Programming Language :: Python :: 3
Classifier: Programming Language :: Python :: 3.9
Classifier: Programming Language :: Python :: 3.10
Classifier: Programming Language :: Python :: 3.11
Classifier: Programming Language :: Python :: 3.12
Requires-Dist: langchain-core (>=0.3.20,<0.4.0)
Requires-Dist: opendataloader-pdf (>=1.1.1)
Project-URL: Homepage, https://github.com/opendataloader-project/opendataloader-pdf
Project-URL: Issues, https://github.com/opendataloader-project/langchain-opendataloader-pdf/issues
Project-URL: Repository, https://github.com/opendataloader-project/langchain-opendataloader-pdf
